nercone_fullcopy/__init__.py
nercone_fullcopy/__main__.py
nercone_fullcopy/cli.py
nercone_fullcopy/copy.py
nercone_fullcopy-0.0.2.dist-info/WHEEL
nercone_fullcopy-0.0.2.dist-info/entry_points.txt
nercone_fullcopy-0.0.2.dist-info/METADATA
nercone_fullcopy-0.0.2.dist-info/RECORD
