Metadata-Version: 2.3
Name: nercone-fullcopy
Version: 0.0.2
Summary: Bit-exact, metadata-preserving copy utility for disks, images, partitions, or volumes.
Author: Nercone
Author-email: Nercone <nercone@diamondgotcat.net>
License: MIT
Classifier: Programming Language :: Python :: 3
Classifier: License :: OSI Approved :: MIT License
Classifier: Operating System :: OS Independent
Requires-Dist: nercone-modern
Requires-Python: >=3.8
